weni_commons/__init__.py
weni_commons-1.1.2.dist-info/LICENSE
weni_commons-1.1.2.dist-info/METADATA
weni_commons-1.1.2.dist-info/WHEEL
weni_commons-1.1.2.dist-info/RECORD
